openinference/instrumentation/haystack/__init__.py
openinference/instrumentation/haystack/_base64.py
openinference/instrumentation/haystack/_wrappers.py
openinference/instrumentation/haystack/version.py
openinference_instrumentation_haystack-0.1.29.dist-info/METADATA
openinference_instrumentation_haystack-0.1.29.dist-info/WHEEL
openinference_instrumentation_haystack-0.1.29.dist-info/entry_points.txt
openinference_instrumentation_haystack-0.1.29.dist-info/licenses/LICENSE
openinference_instrumentation_haystack-0.1.29.dist-info/RECORD
